just_cache/__init__.py
just_cache/_just_cache.py
just_cache-0.1.0.dist-info/METADATA
just_cache-0.1.0.dist-info/WHEEL
just_cache-0.1.0.dist-info/top_level.txt
just_cache-0.1.0.dist-info/RECORD
